bangladeshrailway/__init__.py
bangladeshrailway/bangladeshrailway.py
bangladeshrailway/cli.py
bangladesh_railway_cli-0.1.2.dist-info/METADATA
bangladesh_railway_cli-0.1.2.dist-info/WHEEL
bangladesh_railway_cli-0.1.2.dist-info/entry_points.txt
bangladesh_railway_cli-0.1.2.dist-info/top_level.txt
bangladesh_railway_cli-0.1.2.dist-info/RECORD
