Metadata-Version: 2.2
Name: bangladesh-railway-cli
Version: 0.1.2
Summary: A Python module for Bangladesh Railway's Ticketing System
Author: Md Minhazul Haque
Author-email: mdminhazulhaque@gmail.com
Classifier: Programming Language :: Python :: 3
Classifier: License :: OSI Approved :: MIT License
Classifier: Operating System :: OS Independent
Requires-Python: >=3.6
Dynamic: author
Dynamic: author-email
Dynamic: classifier
Dynamic: description
Dynamic: description-content-type
Dynamic: requires-python
Dynamic: summary
